steamfitter/__about__.py
steamfitter/__init__.py
steamfitter/ihme_deps.py
steamfitter/parallel.py
steamfitter/paths.py
steamfitter/shell_tools.py
steamfitter/cli_tools/__init__.py
steamfitter/cli_tools/decorators.py
steamfitter/cli_tools/logging.py
steamfitter/cli_tools/metadata.py
steamfitter/cli_tools/run_directory.py
steamfitter/cli_tools/validation.py
steamfitter/workflow/__init__.py
steamfitter/workflow/specification.py
steamfitter/workflow/template.py
steamfitter/workflow/utilities.py
steamfitter-0.0.1.dist-info/LICENSE
steamfitter-0.0.1.dist-info/METADATA
steamfitter-0.0.1.dist-info/WHEEL
steamfitter-0.0.1.dist-info/top_level.txt
steamfitter-0.0.1.dist-info/RECORD
