Metadata-Version: 2.1
Name: steamfitter
Version: 0.0.1
Summary: steamfitter is a set of tools for building and maintaining high-throughput data and modeling pipelines
Home-page: https://github.com/ihmeuw/steamfitter
Author: The IHME Rapid Response Team
Author-email: collijk@uw.edu
License: BSD-3-Clause
License-File: LICENSE
Requires-Dist: click
Requires-Dist: loguru
Requires-Dist: numpy
Requires-Dist: pandas
Requires-Dist: pathos
Requires-Dist: pyyaml (>=5.1)
Requires-Dist: tqdm
Provides-Extra: dev
Requires-Dist: sphinx (>=4.0) ; extra == 'dev'
Requires-Dist: sphinx-rtd-theme ; extra == 'dev'
Requires-Dist: sphinx-click ; extra == 'dev'
Requires-Dist: pytest ; extra == 'dev'
Requires-Dist: pytest-mock ; extra == 'dev'
Requires-Dist: black ; extra == 'dev'
Requires-Dist: isort ; extra == 'dev'
Provides-Extra: docs
Requires-Dist: sphinx (>=4.0) ; extra == 'docs'
Requires-Dist: sphinx-rtd-theme ; extra == 'docs'
Requires-Dist: sphinx-click ; extra == 'docs'
Provides-Extra: internal
Requires-Dist: jobmon[ihme] (==3.0.5) ; extra == 'internal'
Requires-Dist: db-queries (<26,>=25.2.0) ; extra == 'internal'
Provides-Extra: test
Requires-Dist: pytest ; extra == 'test'
Requires-Dist: pytest-mock ; extra == 'test'
